{
  "version": "0.9.6",
  "task_type": "det",
  "shapes": [
    {
      "label": "MetalSheet",
      "points": [
        [
          7.376068376068375,
          21.03133903133903
        ],
        [
          60.22507122507122,
          90.11965811965811
        ]
      ],
      "shape_type": "rectangle",
      "flags": {},
      "group_id": null,
      "other_data": {}
    },
    {
      "label": "Bead",
      "points": [
        [
          13.786324786324784,
          24.735042735042732
        ],
        [
          26.179487179487175,
          37.982905982905976
        ]
      ],
      "shape_type": "rectangle",
      "flags": {},
      "group_id": null,
      "other_data": {}
    },
    {
      "label": "Bead",
      "points": [
        [
          28.03133903133903,
          24.165242165242162
        ],
        [
          39.427350427350426,
          36.84330484330484
        ]
      ],
      "shape_type": "rectangle",
      "flags": {},
      "group_id": null,
      "other_data": {}
    },
    {
      "label": "Bead",
      "points": [
        [
          42.13390313390313,
          24.450142450142444
        ],
        [
          54.52706552706552,
          37.27065527065527
        ]
      ],
      "shape_type": "rectangle",
      "flags": {},
      "group_id": null,
      "other_data": {}
    },
    {
      "label": "Bead",
      "points": [
        [
          13.074074074074073,
          70.6039886039886
        ],
        [
          24.897435897435898,
          85.13390313390313
        ]
      ],
      "shape_type": "rectangle",
      "flags": {},
      "group_id": null,
      "other_data": {}
    },
    {
      "label": "Bead",
      "points": [
        [
          25.609686609686605,
          71.03133903133903
        ],
        [
          39.71225071225071,
          85.56125356125355
        ]
      ],
      "shape_type": "rectangle",
      "flags": {},
      "group_id": null,
      "other_data": {}
    },
    {
      "label": "Bead",
      "points": [
        [
          41.99145299145299,
          72.74074074074073
        ],
        [
          55.096866096866094,
          86.13105413105413
        ]
      ],
      "shape_type": "rectangle",
      "flags": {},
      "group_id": null,
      "other_data": {}
    }
  ],
  "imageHeight": 100,
  "imageWidth": 100,
  "imageDepth": 4,
  "split": "train"
}