{
  "version": "0.9.6",
  "task_type": "det",
  "shapes": [
    {
      "label": "MetalSheet",
      "points": [
        [
          0.25356125356125325,
          25.447293447293447
        ],
        [
          64.2136752136752,
          80.14814814814814
        ]
      ],
      "shape_type": "rectangle",
      "flags": {},
      "group_id": null,
      "other_data": {}
    },
    {
      "label": "Bead",
      "points": [
        [
          12.646723646723647,
          42.256410256410255
        ],
        [
          0.0,
          31.0
        ]
      ],
      "shape_type": "rectangle",
      "flags": {},
      "group_id": null,
      "other_data": {}
    },
    {
      "label": "Bead",
      "points": [
        [
          11.222222222222221,
          57.35612535612535
        ],
        [
          0.0,
          47.0
        ]
      ],
      "shape_type": "rectangle",
      "flags": {},
      "group_id": null,
      "other_data": {}
    },
    {
      "label": "Bead",
      "points": [
        [
          10.225071225071222,
          73.59544159544159
        ],
        [
          0.0,
          61.0
        ]
      ],
      "shape_type": "rectangle",
      "flags": {},
      "group_id": null,
      "other_data": {}
    },
    {
      "label": "Bead",
      "points": [
        [
          44.55555555555555,
          32.28490028490028
        ],
        [
          58.943019943019934,
          43.53846153846153
        ]
      ],
      "shape_type": "rectangle",
      "flags": {},
      "group_id": null,
      "other_data": {}
    },
    {
      "label": "Bead",
      "points": [
        [
          44.55555555555555,
          46.52991452991452
        ],
        [
          60.65242165242165,
          58.92307692307692
        ]
      ],
      "shape_type": "rectangle",
      "flags": {},
      "group_id": null,
      "other_data": {}
    },
    {
      "label": "Bead",
      "points": [
        [
          43.98575498575498,
          62.199430199430196
        ],
        [
          60.50997150997151,
          73.59544159544159
        ]
      ],
      "shape_type": "rectangle",
      "flags": {},
      "group_id": null,
      "other_data": {}
    }
  ],
  "imageHeight": 100,
  "imageWidth": 100,
  "imageDepth": 4,
  "split": "valid"
}