{
  "version": "0.9.6",
  "task_type": "det",
  "shapes": [
    {
      "label": "Bead",
      "points": [
        [
          21.200000000000003,
          25.5
        ],
        [
          34.7,
          36.5
        ]
      ],
      "shape_type": "rectangle",
      "flags": {},
      "group_id": null,
      "other_data": {}
    },
    {
      "label": "Bead",
      "points": [
        [
          20.299999999999997,
          40.3
        ],
        [
          33.7,
          52.3
        ]
      ],
      "shape_type": "rectangle",
      "flags": {},
      "group_id": null,
      "other_data": {}
    },
    {
      "label": "Bead",
      "points": [
        [
          20.099999999999994,
          55.2
        ],
        [
          32.8,
          66.9
        ]
      ],
      "shape_type": "rectangle",
      "flags": {},
      "group_id": null,
      "other_data": {}
    },
    {
      "label": "Bead",
      "points": [
        [
          69.1,
          25.0
        ],
        [
          81.19999999999999,
          36.400000000000006
        ]
      ],
      "shape_type": "rectangle",
      "flags": {},
      "group_id": null,
      "other_data": {}
    },
    {
      "label": "Bead",
      "points": [
        [
          68.0,
          55.2
        ],
        [
          80.9,
          67.1
        ]
      ],
      "shape_type": "rectangle",
      "flags": {},
      "group_id": null,
      "other_data": {}
    },
    {
      "label": "Bead",
      "points": [
        [
          67.5,
          37.599999999999994
        ],
        [
          80.0,
          51.2
        ]
      ],
      "shape_type": "rectangle",
      "flags": {},
      "group_id": null,
      "other_data": {}
    },
    {
      "label": "MetalSheet",
      "points": [
        [
          15.200000000000003,
          19.400000000000006
        ],
        [
          80.9,
          72.9
        ]
      ],
      "shape_type": "rectangle",
      "flags": {},
      "group_id": null,
      "other_data": {}
    }
  ],
  "imageHeight": 100,
  "imageWidth": 100,
  "imageDepth": 4,
  "split": "valid"
}