{
  "version": "0.9.6",
  "task_type": "det",
  "shapes": [
    {
      "label": "MetalSheet",
      "points": [
        [
          13.136286201022145,
          19.596252129471893
        ],
        [
          80.59795570698466,
          76.1550255536627
        ]
      ],
      "shape_type": "rectangle",
      "flags": {},
      "group_id": null,
      "other_data": {}
    },
    {
      "label": "Bead",
      "points": [
        [
          16.156729131175467,
          26.926746166950593
        ],
        [
          28.252129471890967,
          38.51107325383305
        ]
      ],
      "shape_type": "rectangle",
      "flags": {},
      "group_id": null,
      "other_data": {}
    },
    {
      "label": "Bead",
      "points": [
        [
          16.156729131175467,
          40.21465076660988
        ],
        [
          29.78534923339012,
          52.99148211243612
        ]
      ],
      "shape_type": "rectangle",
      "flags": {},
      "group_id": null,
      "other_data": {}
    },
    {
      "label": "Bead",
      "points": [
        [
          17.51959114139693,
          57.93185689948892
        ],
        [
          32.17035775127768,
          67.47189097103919
        ]
      ],
      "shape_type": "rectangle",
      "flags": {},
      "group_id": null,
      "other_data": {}
    },
    {
      "label": "Bead",
      "points": [
        [
          62.834752981260635,
          26.756388415672916
        ],
        [
          76.63373083475298,
          38.34071550255537
        ]
      ],
      "shape_type": "rectangle",
      "flags": {},
      "group_id": null,
      "other_data": {}
    },
    {
      "label": "Bead",
      "points": [
        [
          62.66439522998297,
          42.08858603066439
        ],
        [
          75.95229982964224,
          54.35434412265758
        ]
      ],
      "shape_type": "rectangle",
      "flags": {},
      "group_id": null,
      "other_data": {}
    },
    {
      "label": "Bead",
      "points": [
        [
          61.81260647359454,
          57.76149914821124
        ],
        [
          76.12265758091993,
          69.51618398637137
        ]
      ],
      "shape_type": "rectangle",
      "flags": {},
      "group_id": null,
      "other_data": {}
    }
  ],
  "imageHeight": 100,
  "imageWidth": 100,
  "imageDepth": 4,
  "split": "train"
}