{
  "version": "0.9.6",
  "task_type": "det",
  "shapes": [
    {
      "label": "MetalSheet",
      "points": [
        [
          7.173764906303234,
          19.08517887563884
        ],
        [
          77.02044293015332,
          76.1550255536627
        ]
      ],
      "shape_type": "rectangle",
      "flags": {},
      "group_id": null,
      "other_data": {}
    },
    {
      "label": "Bead",
      "points": [
        [
          11.21635434412265,
          27.608177172061332
        ],
        [
          22.630323679727425,
          39.70357751277683
        ]
      ],
      "shape_type": "rectangle",
      "flags": {},
      "group_id": null,
      "other_data": {}
    },
    {
      "label": "Bead",
      "points": [
        [
          11.557069846678019,
          42.770017035775126
        ],
        [
          24.333901192504257,
          53.332197614991486
        ]
      ],
      "shape_type": "rectangle",
      "flags": {},
      "group_id": null,
      "other_data": {}
    },
    {
      "label": "Bead",
      "points": [
        [
          10.875638841567294,
          57.420783645655874
        ],
        [
          23.311754684838164,
          68.49403747870528
        ]
      ],
      "shape_type": "rectangle",
      "flags": {},
      "group_id": null,
      "other_data": {}
    },
    {
      "label": "Bead",
      "points": [
        [
          56.53151618398637,
          25.56388415672913
        ],
        [
          70.50085178875639,
          36.63713798977854
        ]
      ],
      "shape_type": "rectangle",
      "flags": {},
      "group_id": null,
      "other_data": {}
    },
    {
      "label": "Bead",
      "points": [
        [
          55.509369676320276,
          41.74787052810903
        ],
        [
          69.30834752981261,
          51.45826235093696
        ]
      ],
      "shape_type": "rectangle",
      "flags": {},
      "group_id": null,
      "other_data": {}
    },
    {
      "label": "Bead",
      "points": [
        [
          58.91652470187394,
          56.73935264054515
        ],
        [
          72.03407155025553,
          68.66439522998297
        ]
      ],
      "shape_type": "rectangle",
      "flags": {},
      "group_id": null,
      "other_data": {}
    }
  ],
  "imageHeight": 100,
  "imageWidth": 100,
  "imageDepth": 4,
  "split": "train"
}