{
  "version": "0.9.6",
  "task_type": "det",
  "shapes": [
    {
      "label": "MetalSheet",
      "points": [
        [
          15.200000000000003,
          25.200000000000003
        ],
        [
          105.0,
          92.30000000000001
        ]
      ],
      "shape_type": "rectangle",
      "flags": {},
      "group_id": null,
      "other_data": {}
    },
    {
      "label": "Bead",
      "points": [
        [
          24.9,
          32.2
        ],
        [
          44.3,
          47.900000000000006
        ]
      ],
      "shape_type": "rectangle",
      "flags": {},
      "group_id": null,
      "other_data": {}
    },
    {
      "label": "Bead",
      "points": [
        [
          24.200000000000003,
          53.900000000000006
        ],
        [
          37.599999999999994,
          68.7
        ]
      ],
      "shape_type": "rectangle",
      "flags": {},
      "group_id": null,
      "other_data": {}
    },
    {
      "label": "Bead",
      "points": [
        [
          21.6,
          72.4
        ],
        [
          41.0,
          86.2
        ]
      ],
      "shape_type": "rectangle",
      "flags": {},
      "group_id": null,
      "other_data": {}
    },
    {
      "label": "Bead",
      "points": [
        [
          80.5,
          72.4
        ],
        [
          97.19999999999999,
          86.9
        ]
      ],
      "shape_type": "rectangle",
      "flags": {},
      "group_id": null,
      "other_data": {}
    },
    {
      "label": "Bead",
      "points": [
        [
          82.6,
          53.3
        ],
        [
          102.19999999999999,
          69.0
        ]
      ],
      "shape_type": "rectangle",
      "flags": {},
      "group_id": null,
      "other_data": {}
    },
    {
      "label": "Bead",
      "points": [
        [
          83.6,
          32.400000000000006
        ],
        [
          101.6,
          49.0
        ]
      ],
      "shape_type": "rectangle",
      "flags": {},
      "group_id": null,
      "other_data": {}
    }
  ],
  "imageHeight": 120,
  "imageWidth": 120,
  "imageDepth": 4,
  "split": "valid"
}