{
  "version": "0.9.6",
  "task_type": "det",
  "shapes": [
    {
      "label": "MetalSheet",
      "points": [
        [
          34.0,
          20.700000000000003
        ],
        [
          119.0,
          91.0
        ]
      ],
      "shape_type": "rectangle",
      "flags": {},
      "group_id": null,
      "other_data": {}
    },
    {
      "label": "Bead",
      "points": [
        [
          36.900000000000006,
          25.299999999999997
        ],
        [
          53.5,
          41.8
        ]
      ],
      "shape_type": "rectangle",
      "flags": {},
      "group_id": null,
      "other_data": {}
    },
    {
      "label": "Bead",
      "points": [
        [
          39.3,
          48.8
        ],
        [
          52.3,
          62.5
        ]
      ],
      "shape_type": "rectangle",
      "flags": {},
      "group_id": null,
      "other_data": {}
    },
    {
      "label": "Bead",
      "points": [
        [
          35.599999999999994,
          69.0
        ],
        [
          51.900000000000006,
          84.8
        ]
      ],
      "shape_type": "rectangle",
      "flags": {},
      "group_id": null,
      "other_data": {}
    },
    {
      "label": "Bead",
      "points": [
        [
          98.6,
          67.7
        ],
        [
          115.1,
          84.4
        ]
      ],
      "shape_type": "rectangle",
      "flags": {},
      "group_id": null,
      "other_data": {}
    },
    {
      "label": "Bead",
      "points": [
        [
          96.80000000000001,
          45.900000000000006
        ],
        [
          113.80000000000001,
          63.2
        ]
      ],
      "shape_type": "rectangle",
      "flags": {},
      "group_id": null,
      "other_data": {}
    },
    {
      "label": "Bead",
      "points": [
        [
          96.6,
          27.700000000000003
        ],
        [
          113.30000000000001,
          44.0
        ]
      ],
      "shape_type": "rectangle",
      "flags": {},
      "group_id": null,
      "other_data": {}
    }
  ],
  "imageHeight": 120,
  "imageWidth": 120,
  "imageDepth": 4,
  "split": "valid"
}